python_tap/__init__.py
python_tap/py.typed
python_tap/decorator/__init__.py
python_tap/decorator/core.py
python_tap/store/__init__.py
python_tap/store/core.py
python_tap/taps/__init__.py
python_tap/taps/params.py
python_tap-0.1.3.dist-info/METADATA
python_tap-0.1.3.dist-info/WHEEL
python_tap-0.1.3.dist-info/licenses/LICENSE
python_tap-0.1.3.dist-info/RECORD
