Metadata-Version: 2.4
Name: python-tap
Version: 0.1.3
Summary: A Python implementation of tap. Useful for REPL Driven Development.
Project-URL: Repository, https://github.com/DavidVujic/python-tap
Author: David Vujic
License-File: LICENSE
Requires-Python: >=3.10
